a5-client-utils/__init__.py
a5-client-utils/util.py
a5_client_utils/__init__.py
a5_client_utils/util.py
a5_client_utils/descriptors/__init__.py
a5_client_utils/descriptors/bool_descriptor.py
a5_client_utils/descriptors/bool_or_none_descriptor.py
a5_client_utils/descriptors/dataframe_descriptor.py
a5_client_utils/descriptors/datetime_descriptor.py
a5_client_utils/descriptors/dict_descriptor.py
a5_client_utils/descriptors/duration_descriptor.py
a5_client_utils/descriptors/duration_descriptor_default_none.py
a5_client_utils/descriptors/filepath_descriptor.py
a5_client_utils/descriptors/float_descriptor.py
a5_client_utils/descriptors/int_descriptor.py
a5_client_utils/descriptors/list_descriptor.py
a5_client_utils/descriptors/list_or_dict_descriptor.py
a5_client_utils/descriptors/string_descriptor.py
a5_client_utils/types/__init__.py
a5_client_utils/types/api_config_dict.py
a5_client_utils/types/corrida_dict.py
a5_client_utils/types/series_dict.py
a5_client_utils/types/series_prono_dict.py
a5_client_utils/types/tvp.py
a5_client_utils/types/typed_list.py
a5_client_utils-0.1.1.dist-info/METADATA
a5_client_utils-0.1.1.dist-info/WHEEL
a5_client_utils-0.1.1.dist-info/top_level.txt
a5_client_utils-0.1.1.dist-info/RECORD
