Metadata-Version: 2.1
Name: a5_client_utils
Version: 0.1.1
Summary: Auxiliary functions for a5 API clients
Home-page: https://github.com/jbianchi81/a5-client-utils
Author: Juan F. Bianchi
Author-email: jbianchi@ina.gob.ar
License: UNKNOWN
Platform: UNKNOWN
